.coveragerc
.gitignore
CHANGES.rst
MANIFEST.in
README.rst
setup.py
websauna/__init__.py
websauna.viewconfig.egg-info/PKG-INFO
websauna.viewconfig.egg-info/SOURCES.txt
websauna.viewconfig.egg-info/dependency_links.txt
websauna.viewconfig.egg-info/namespace_packages.txt
websauna.viewconfig.egg-info/requires.txt
websauna.viewconfig.egg-info/top_level.txt
websauna/viewconfig/__init__.py