Metadata-Version: 1.1
Name: websauna.viewconfig
Version: 0.1.3
Summary: View override configuration pattern for Pyramid framework
Home-page: https://bitbucket.org/websauna/websauna.viewconfig
Author: Mikko Ohtamaa
Author-email: mikko@opensourcehacker.com
License: MIT
Keywords: pyramid
Platform: UNKNOWN
Classifier: Development Status :: 3 - Alpha
Classifier: Intended Audience :: Developers
Classifier: Topic :: Software Development :: Libraries
Classifier: License :: OSI Approved :: MIT License
Classifier: Framework :: Pyramid
Classifier: Programming Language :: Python :: 3
Classifier: Programming Language :: Python :: 3.3
Classifier: Programming Language :: Python :: 3.4
Classifier: Programming Language :: Python :: 3.5
